{
    "Title": "Update AvailableтЪб",
    "versionCode": "82",
    "versionName": "5.0.4",
    "updateSize": "2 MB",
    "releaseDate": "May 8, 2025",
    "Msg": "ржЕржирзЗржХ ржлрзНрж░рж┐ ржЪрж╛рж▓рж╛ржЗржЫрзЛ\nтАв ржПржЦржи ржЖржкржбрзЗржЯ ржХрж░рзЛ\nтАв ржирждрзБржи ржнрж╛рж░рзНрж╕ржи ржП ржЕржирзЗржХ ржлрж┐ржЪрж╛рж░рж╕ ржПржб ржХрж░рж╛ рж╣ржпрж╝рзЗржЫрзЗ\nтАв  ЁЯОЙ What's New:\nтАв Improved user interface\nтАв Added new features\nтАв Bug fixes and performance improvements\nтАв Enhanced security",
    "downloadLink": "https://wa.me/message/7VHYQWG44MGEA1"
}
